<?xml version="1.0" encoding="UTF-8"?>
<ValueSet xmlns="http://hl7.org/fhir">
  <id value="input-type"/>
  <url value="https://specifications.openehr.org/fhir/valueset-input-type"/>
  <version value="3.1.0"/>
  <name value="InputTypeVS"/>
  <title value="Input Type ValueSet"/>
  <status value="active"/>
  <experimental value="false"/>
  <date value="2024-08-22"/>
  <publisher value="openEHR International"/>
  <contact>
    <name value="openEHR TERM specifications"/>
  </contact>
  <description value="Input Type ValueSet"/>
  <compose>
    <include>
      <system value="https://specifications.openehr.org/fhir/codesystem-input-type"/>
    </include>
  </compose>
</ValueSet>
